{
	"items":{
		"special": {
			"best_girl": {
				"name": "⭐Самая лучшая девочка⭐",
				"price": 0,
				"max_count": 1,
				"can_sell": false,
				"can_buy": false,
				"hidden": false
			},
			"new_year_2020_1": {
				"name": "⭐Календарь 2020⭐",
				"price": 1000000,
				"max_count": 1,
				"can_sell": true,
				"can_buy": false,
				"hidden": false
			},
			"new_year_2020_2": {
				"name": "⭐Магнитик 2020⭐",
				"price": 1000000,
				"max_count": 1,
				"can_sell": true,
				"can_buy": false,
				"hidden": false
			},
			"new_year_2020_3": {
				"name": "⭐Оливьешка 2020⭐",
				"price": 1000000,
				"max_count": 1,
				"can_sell": true,
				"can_buy": false,
				"hidden": false
			},
			"new_year_2020_tangerine": {
				"name": "⭐Мандаринка 2020⭐",
				"price": 3000000,
				"max_count": 1,
				"can_sell": true,
				"can_buy": false,
				"hidden": false
			}
		},

		"govdoc": {
			"presidential_certificate":{
				"name": "Удостоверение президента",
				"price": 0,
				"max_count": 1,
				"can_sell": false,
				"can_buy": false,
				"hidden": false
			}
		},

		"car":{
			"level_1": {
				"name": "Лада-2106",
				"price": 50000,
				"max_count": 1,
				"can_sell": true,
				"can_buy": true,
				"hidden": false
			},
			"level_2": {
				"name": "УАЗ-452 \"Буханка\"",
				"price": 75000,
				"max_count": 1,
				"can_sell": true,
				"can_buy": true,
				"hidden": false
			},
			"level_3": {
				"name": "ЗАЗ-968 \"Запорожец\"",
				"price": 100000,
				"max_count": 1,
				"can_sell": true,
				"can_buy": true,
				"hidden": false
			},
			"level_4": {
				"name": "Mitsubishi Lancer",
				"price": 200000,
				"max_count": 1,
				"can_sell": true,
				"can_buy": true,
				"hidden": false
			},
			"level_5": {
				"name": "Audi A6",
				"price": 350000,
				"max_count": 1,
				"can_sell": true,
				"can_buy": true,
				"hidden": false
			},
			"level_6": {
				"name": "Isuzu Bighorn",
				"price": 650000,
				"max_count": 1,
				"can_sell": true,
				"can_buy": true,
				"hidden": false
			},
			"level_7": {
				"name": "BMW X6",
				"price": 800000,
				"max_count": 1,
				"can_sell": true,
				"can_buy": true,
				"hidden": false
			},
			"level_8": {
				"name": "Toyota Supra",
				"price": 1500000,
				"max_count": 1,
				"can_sell": true,
				"can_buy": true,
				"hidden": false
			},
			"level_9": {
				"name": "Infiniti M37",
				"price": 2000000,
				"max_count": 1,
				"can_sell": true,
				"can_buy": true,
				"hidden": false
			},
			"level_10": {
				"name": "Aston Martin Vantage",
				"price": 5600000,
				"max_count": 1,
				"can_sell": true,
				"can_buy": true,
				"hidden": false
			},
			"level_11": {
				"name": "Mercedes-Benz SLR McLaren",
				"price": 7000000,
				"max_count": 1,
				"can_sell": true,
				"can_buy": true,
				"hidden": false
			},
			"level_12": {
				"name": "Nissan Primera",
				"price": 780000,
				"max_count": 1,
				"can_sell": true,
				"can_buy": false,
				"hidden": true
			},
			"level_13": {
				"name": "Subaru Impreza WRX",
				"price": 965000,
				"max_count": 1,
				"can_sell": true,
				"can_buy": false,
				"hidden": true
			},
			"level_14": {
				"name": "Infinity G35",
				"price": 1247000,
				"max_count": 1,
				"can_sell": true,
				"can_buy": false,
				"hidden": true
			}
		},

		"immovables": {
			"level_1": {
				"name": "Номер в мотеле",
				"price": 5000,
				"max_count": 1,
				"can_sell": true,
				"can_buy": true,
				"hidden": false
			},
			"level_2": {
				"name": "Комната в гетто-районе",
				"price": 25000,
				"max_count": 1,
				"can_sell": true,
				"can_buy": true,
				"hidden": false
			},
			"level_3": {
				"name": "Двухкомнатная квартира в городе",
				"price": 175000,
				"max_count": 1,
				"can_sell": true,
				"can_buy": true,
				"hidden": false
			},
			"level_4": {
				"name": "Трёхкомнатная квартира в столице",
				"price": 900000,
				"max_count": 1,
				"can_sell": true,
				"can_buy": true,
				"hidden": false
			},
			"level_5": {
				"name": "Шестикомнатная квартира в столице",
				"price": 3500000,
				"max_count": 1,
				"can_sell": true,
				"can_buy": true,
				"hidden": false
			},
			"level_6": {
				"name": "Вилла в Комо",
				"price": 54000000,
				"max_count": 1,
				"can_sell": true,
				"can_buy": true,
				"hidden": false
			},
			"level_7": {
				"name": "Аппартаменты во Франции",
				"price": 186500000,
				"max_count": 1,
				"can_sell": true,
				"can_buy": true,
				"hidden": false
			},
			"level_8": {
				"name": "Жилой комплекс в Лос Анжелесе",
				"price": 436000000,
				"max_count": 1,
				"can_sell": true,
				"can_buy": true,
				"hidden": false
			},
			"level_80": {
				"name": "Дом Олега",
				"price": 10000000000,
				"max_count": 1,
				"can_sell": true,
				"can_buy": true,
				"hidden": false
			}
		},

		"phone": {
			"level_1": {
				"name": "Nokia 3310",
				"price": 2500,
				"max_count": 1,
				"can_sell": true,
				"can_buy": true,
				"hidden": false
			},
			"level_2": {
				"name": "Samsung X510",
				"price": 5000,
				"max_count": 1,
				"can_sell": true,
				"can_buy": true,
				"hidden": false
			},
			"level_3": {
				"name": "Sony Ericsson K750i",
				"price": 8500,
				"max_count": 1,
				"can_sell": true,
				"can_buy": true,
				"hidden": false
			},
			"level_4": {
				"name": "Apple iPhone 2G",
				"price": 14999,
				"max_count": 1,
				"can_sell": true,
				"can_buy": true,
				"hidden": false
			},
			"level_5": {
				"name": "Apple iPhone 5s",
				"price": 24999,
				"max_count": 1,
				"can_sell": true,
				"can_buy": true,
				"hidden": false
			},
			"level_6": {
				"name": "Apple iPhone 6s",
				"price": 39999,
				"max_count": 1,
				"can_sell": true,
				"can_buy": true,
				"hidden": false
			},
			"level_7": {
				"name": "Apple iPhone 8 Plus",
				"price": 74999,
				"max_count": 1,
				"can_sell": true,
				"can_buy": true,
				"hidden": false
			},
			"level_8": {
				"name": "Apple iPhone 10 XS Max",
				"price": 119999,
				"max_count": 1,
				"can_sell": true,
				"can_buy": true,
				"hidden": false
			},
			"level_9": {
				"name": "Apple iPhone 11 Pro Max",
				"price": 239999,
				"max_count": 1,
				"can_sell": true,
				"can_buy": true,
				"hidden": false
			},
			"level_10": {
				"name": "Apple iPhone 12 XS Ultra Pro Max Edition",
				"price": 889999,
				"max_count": 1,
				"can_sell": true,
				"can_buy": true,
				"hidden": false
			},
			"level_11": {
				"name": "Apple iPhone 13 Pro Mega",
				"price": 5000000,
				"max_count": 1,
				"can_sell": true,
				"can_buy": true,
				"hidden": false
			}
		},

		"edu": {
			"level_1": {
				"name": "Начальное образование",
				"price": 10000,
				"max_count": 1,
				"can_sell": false,
				"can_buy": true,
				"hidden": true
			},
			"level_2": {
				"name": "Полное среднее образование",
				"price": 30000,
				"max_count": 1,
				"can_sell": false,
				"can_buy": true,
				"hidden": true
			},
			"level_3": {
				"name": "Профессиональное среднее образование",
				"price": 100000,
				"max_count": 1,
				"can_sell": false,
				"can_buy": true,
				"hidden": true
			},
			"level_4": {
				"name": "Бакалавриат высшего образования",
				"price": 250000,
				"max_count": 1,
				"can_sell": false,
				"can_buy": true,
				"hidden": true
			},
			"level_5": {
				"name": "Магистр высшего образования",
				"price": 700000,
				"max_count": 1,
				"can_sell": false,
				"can_buy": true,
				"hidden": true
			},
			"level_6": {
				"name": "Кандидат наук",
				"price": 3000000,
				"max_count": 1,
				"can_sell": false,
				"can_buy": true,
				"hidden": true
			},
			"level_7": {
				"name": "Доктор наук",
				"price": 9000000,
				"max_count": 1,
				"can_sell": false,
				"can_buy": true,
				"hidden": true
			}
		}
	},

	"shop_sections":[
		{
			"name": "Автомобиль",
			"type": "item",
			"items": "car"
		},
		{
			"name": "Недвижимость",
			"type": "item",
			"items": "immovables"
		},
		{
			"name": "Телефон",
			"type": "item",
			"items": "phone"
		}
	],

	"enterprise_types": {
	    "shop": {
	      	"name": "Магазин",
	      	"price": 1500000,
	      	"initial_workers": 5,
	      	"improvment":{
	      		"workers": [
		      		{
		      			"name": "Улучшение условий рабочих Ⅰ",
			          	"duration": 7200,
			          	"workers_required": 5,
			          	"exp_required": 50,
			          	"cost": 20000,
			          	"new_workers": 5
		      		},
		      		{
		      			"name": "Улучшение условий рабочих Ⅱ",
			          	"duration": 14400,
			          	"workers_required": 10,
			          	"exp_required": 100,
			          	"cost": 45000,
			          	"new_workers": 10
		      		},
		      		{
		      			"name": "Улучшение условий рабочих Ⅲ",
			          	"duration": 28800,
			          	"workers_required": 20,
			          	"exp_required": 390,
			          	"cost": 80000,
			          	"new_workers": 30
		      		},
		      		{
		      			"name": "Улучшение условий рабочих Ⅳ",
			          	"duration": 43200,
			          	"workers_required": 50,
			          	"exp_required": 1000,
			          	"cost": 170000,
			          	"new_workers": 30
		      		},
		      		{
		      			"name": "Улучшение условий рабочих Ⅴ",
			          	"duration": 57600,
			          	"workers_required": 80,
			          	"exp_required": 2480,
			          	"cost": 400000,
			          	"new_workers": 30
		      		},
		      		{
		      			"name": "Улучшение условий рабочих Ⅵ",
			          	"duration": 72000,
			          	"workers_required": 110,
			          	"exp_required": 3180,
			          	"cost": 780000,
			          	"new_workers": 55
		      		}
	      		],
		      	"contracts": [
		      		{
		      			"name": "Расширение торговой сети Ⅰ",
			          	"duration": 21600,
			          	"workers_required": 20,
			          	"exp_required": 450,
			          	"cost": 125000
		      		},
		      		{
		      			"name": "Расширение торговой сети II",
			          	"duration": 64800,
			          	"workers_required": 165,
			          	"exp_required": 5920,
			          	"cost": 800000
		      		}
		      	]
	      	},
	      	"contracts": [
		        {
		          	"name": "Продажа товаров Ⅰ",
		          	"duration": 5400,
		          	"workers_required": 5,
		          	"cost": 2500,
		          	"income": 3850,
		          	"exp": 10
		        },
		        {
		          	"name": "Продажа товаров Ⅱ",
		          	"duration": 7200,
		          	"workers_required": 15,
		          	"cost": 6950,
		          	"income": 9650,
		          	"exp": 30
		        },
		        {
		          	"name": "Продажа товаров Ⅲ",
		          	"duration": 12600,
		          	"workers_required": 25,
		          	"cost": 15500,
		          	"income": 24005,
		          	"exp": 50
		        },
		        {
		          	"name": "Продажа товаров Ⅳ",
		          	"duration": 25200,
		          	"workers_required": 50,
		          	"cost": 44750,
		          	"income": 75410,
		          	"exp": 210
		        },
		        {
		          	"name": "Продажа товаров Ⅴ",
		          	"duration": 50400,
		          	"workers_required": 90,
		          	"cost": 185400,
		          	"income": 307200,
		          	"exp": 320
		        }
	        ]
	    }
  	}
}